chan_agent/__init__.py
chan_agent/base_agent.py
chan_agent/base_tool.py
chan_agent/config.py
chan_agent/fc_agent.py
chan_agent/logger.py
chan_agent/schema.py
chan_agent/task_llm.py
chan_agent/llm_track/__init__.py
chan_agent/llm_track/db_tracker.py
chan_agent/llm_track/json_tracker.py
chan_agent/llm_track/warp.py
chan_agent/llms/__init__.py
chan_agent/llms/async_base.py
chan_agent/llms/async_openai.py
chan_agent/llms/async_vertex.py
chan_agent/llms/base.py
chan_agent/llms/gemini.py
chan_agent/llms/openai.py
chan_agent/llms/vertex.py
chan_agent/utils/__init__.py
chan_agent/utils/image.py
chan_agent/utils/messages_processing.py
chan_agent-0.0.16.dist-info/METADATA
chan_agent-0.0.16.dist-info/WHEEL
chan_agent-0.0.16.dist-info/top_level.txt
chan_agent-0.0.16.dist-info/RECORD
