Metadata-Version: 2.1
Name: chan-agent
Version: 0.0.16
Summary: A simple llm agent
Home-page: https://github.com/Chan-0312/chan-agent
Author: Chan
Author-email: 925355568@qq.com
Classifier: Programming Language :: Python :: 3
Classifier: License :: OSI Approved :: MIT License
Classifier: Operating System :: OS Independent
Requires-Python: >=3.11
Requires-Dist: openai
Requires-Dist: instructor
Requires-Dist: google-generativeai
Requires-Dist: filelock
Requires-Dist: peewee
